OptimalCluster/__init__.py
OptimalCluster/opticlust.py
OptimalCluster-0.1.0.dist-info/LICENSE
OptimalCluster-0.1.0.dist-info/METADATA
OptimalCluster-0.1.0.dist-info/WHEEL
OptimalCluster-0.1.0.dist-info/top_level.txt
OptimalCluster-0.1.0.dist-info/RECORD
